mkgendocs/__init__.py
mkgendocs/__version__.py
mkgendocs/gendocs.py
mkgendocs/parse.py
mkgendocs-0.9.1.dist-info/entry_points.txt
mkgendocs-0.9.1.dist-info/WHEEL
mkgendocs-0.9.1.dist-info/METADATA
mkgendocs-0.9.1.dist-info/RECORD
