Metadata-Version: 2.1
Name: mkgendocs
Version: 0.9.1
Summary: mkgendocs is a Python tool to automate the generation of documentation from docstrings in markdown
Home-page: https://github.com/davidenunes/mkgendocs
License: Apache-2.0
Keywords: mkgendocs,docs,documentation,automation,mkdocs,cli
Author: Davide Nunes
Author-email: davidelnunes@gmail.com
Requires-Python: >=3.7,<4.0
Classifier: Environment :: Console
Classifier: Intended Audience :: Developers
Classifier: Intended Audience :: Education
Classifier: Intended Audience :: Science/Research
Classifier: License :: OSI Approved :: Apache Software License
Classifier: Operating System :: OS Independent
Classifier: Programming Language :: Python
Classifier: Programming Language :: Python :: 3
Classifier: Programming Language :: Python :: 3 :: Only
Classifier: Programming Language :: Python :: 3.10
Classifier: Programming Language :: Python :: 3.5
Classifier: Programming Language :: Python :: 3.6
Classifier: Programming Language :: Python :: 3.7
Classifier: Programming Language :: Python :: 3.8
Classifier: Programming Language :: Python :: 3.9
Classifier: Topic :: Documentation
Classifier: Topic :: Text Processing
Requires-Dist: astor
Requires-Dist: mako
Requires-Dist: pyyaml
Requires-Dist: six
Project-URL: Repository, https://github.com/davidenunes/mkgendocs
